qprof_interfaces/NamedRoutine.py
qprof_interfaces/RoutineWrapper.py
qprof_interfaces/__init__.py
qprof_interfaces/name_routines.py
qprof_interfaces/supports_routine_test.py
qprof_interfaces-1.0.1.dist-info/LICENSE
qprof_interfaces-1.0.1.dist-info/METADATA
qprof_interfaces-1.0.1.dist-info/WHEEL
qprof_interfaces-1.0.1.dist-info/top_level.txt
qprof_interfaces-1.0.1.dist-info/RECORD
