Metadata-Version: 2.1
Name: qprof-interfaces
Version: 1.0.1
Summary: qprof plugin providing the base interfaces.
Home-page: UNKNOWN
Author: Adrien Suau
Author-email: adrien.suau@cerfacs.fr
License: UNKNOWN
Project-URL: Bug Reports, https://gitlab.com/qcomputing/qprof/qprof_interfaces/issues
Project-URL: Source, https://gitlab.com/qcomputing/qprof/qprof_interfaces
Project-URL: Collaborator, https://cerfacs.fr/en
Keywords: quantum,performance,gprof,profiling,interface
Platform: UNKNOWN
Classifier: Development Status :: 3 - Alpha
Classifier: Intended Audience :: Developers
Classifier: Intended Audience :: Education
Classifier: Intended Audience :: Science/Research
Classifier: Topic :: Scientific/Engineering
Classifier: Topic :: Scientific/Engineering :: Mathematics
Classifier: License :: CeCILL-B Free Software License Agreement (CECILL-B)
Classifier: Natural Language :: English
Classifier: Operating System :: OS Independent
Classifier: Programming Language :: Python :: 3 :: Only
Provides-Extra: dev
Requires-Dist: black ; extra == 'dev'
Requires-Dist: pygments ; extra == 'dev'
Requires-Dist: setuptools ; extra == 'dev'
Requires-Dist: wheel ; extra == 'dev'
Requires-Dist: twine ; extra == 'dev'
